pytest_fastapi_deps/__init__.py
pytest_fastapi_deps-0.2.2.dist-info/entry_points.txt
pytest_fastapi_deps-0.2.2.dist-info/LICENSE
pytest_fastapi_deps-0.2.2.dist-info/WHEEL
pytest_fastapi_deps-0.2.2.dist-info/METADATA
pytest_fastapi_deps-0.2.2.dist-info/RECORD
