Metadata-Version: 2.1
Name: pytest-fastapi-deps
Version: 0.2.2
Summary: A fixture which allows easy replacement of fastapi dependencies for testing
Home-page: https://github.com/pksol/pytest-fastapi-deps
License: MIT
Author: Peter Kogan
Author-email: kogan.peter@gmail.com
Requires-Python: >=3.7,<4.0
Classifier: Development Status :: 5 - Production/Stable
Classifier: Framework :: Pytest
Classifier: Intended Audience :: Developers
Classifier: License :: OSI Approved :: MIT License
Classifier: Operating System :: OS Independent
Classifier: Programming Language :: Python
Classifier: Programming Language :: Python :: 3
Classifier: Programming Language :: Python :: 3.10
Classifier: Programming Language :: Python :: 3.7
Classifier: Programming Language :: Python :: 3.8
Classifier: Programming Language :: Python :: 3.9
Classifier: Topic :: Software Development :: Testing
Requires-Dist: fastapi
Requires-Dist: importlib_metadata (>=4.5.0,<5.0.0); python_version < "3.8"
Requires-Dist: pytest
Project-URL: Repository, https://github.com/pksol/pytest-fastapi-deps
